gear/__init__.py
gear/cli.py
gear/rpc.py
gear/thor/__init__.py
gear/thor/account.py
gear/thor/client.py
gear/thor/request.py
gear/utils/__init__.py
gear/utils/compat.py
gear/utils/keystore.py
gear/utils/singleton.py
gear/utils/thread.py
gear/utils/types.py
web3_gear-2.1.1.dist-info/LICENSE
web3_gear-2.1.1.dist-info/METADATA
web3_gear-2.1.1.dist-info/WHEEL
web3_gear-2.1.1.dist-info/entry_points.txt
web3_gear-2.1.1.dist-info/top_level.txt
web3_gear-2.1.1.dist-info/RECORD
