Metadata-Version: 2.1
Name: web3-gear
Version: 2.1.1
Summary: An adapter between thor-restful and eth-rpc.
Home-page: https://github.com/vechain/web3-gear
Author: Han Xiao
Author-email: smallcpp@foxmail.com
License: MIT
Keywords: thor blockchain ethereum
Platform: UNKNOWN
Classifier: Intended Audience :: Developers
Classifier: Programming Language :: Python :: 3.6
Requires-Python: >=3.6
Requires-Dist: aiohttp
Requires-Dist: click
Requires-Dist: eth-keys
Requires-Dist: eth-utils
Requires-Dist: jsonrpcserver
Requires-Dist: lru-dict
Requires-Dist: pbkdf2
Requires-Dist: pycryptodome
Requires-Dist: requests
Requires-Dist: rlp (==0.6.0)
Requires-Dist: scrypt
Requires-Dist: werkzeug
